coral_protocol/__init__.py
coral_protocol/cli.py
coral_protocol/jar/coral-server-1.0-SNAPSHOT.jar
test_coral_server-0.0.1.dist-info/METADATA
test_coral_server-0.0.1.dist-info/WHEEL
test_coral_server-0.0.1.dist-info/entry_points.txt
test_coral_server-0.0.1.dist-info/top_level.txt
test_coral_server-0.0.1.dist-info/RECORD
