Metadata-Version: 2.1
Name: test-coral-server
Version: 0.0.1
Summary: Python wrapper for Coral Protocol Server
Home-page: https://github.com/Coral-Protocol/coral-server
Author: Coral Protocol Team
Project-URL: Bug Tracker, https://github.com/Coral-Protocol/coral-server/issues
Keywords: coral,protocol,server,wrapper
Classifier: Development Status :: 3 - Alpha
Classifier: Intended Audience :: Developers
Classifier: Programming Language :: Python :: 3
Classifier: Programming Language :: Python :: 3.7
Classifier: Programming Language :: Python :: 3.8
Classifier: Programming Language :: Python :: 3.9
Classifier: Programming Language :: Python :: 3.10
Classifier: Operating System :: OS Independent
Requires-Python: >=3.7
